{
  "settings": {
    "components": {
      "code": false,
      "binaries": false
    },
    "targetId": "net10.0",
    "targetDisplayName": ".NETCoreApp,Version=v10.0"
  },
  "analysisStartTime": "2026-01-28T10:49:41.37109Z",
  "analysisEndTime": "2026-01-28T10:49:41.7950898Z",
  "privacyModeHelpUrl": "https://go.microsoft.com/fwlink/?linkid=2270980",
  "stats": {
    "summary": {
      "projects": 1,
      "issues": 0,
      "incidents": 0,
      "effort": 0
    },
    "charts": {
      "severity": {
        "Mandatory": 0,
        "Optional": 0,
        "Potential": 0,
        "Information": 0
      },
      "category": {}
    }
  },
  "projects": [
    {
      "path": "LogBook.csproj",
      "startingProject": true,
      "issues": 0,
      "storyPoints": 0,
      "properties": {
        "appName": "LogBook",
        "projectKind": "AspNetCore",
        "frameworks": [
          "net10.0"
        ],
        "languages": [
          "C#"
        ],
        "tools": [
          "MSBuild"
        ],
        "isSdkStyle": true,
        "numberOfFiles": 29,
        "numberOfCodeFiles": 21,
        "linesTotal": 1816,
        "linesOfCode": 934,
        "totalApiScanned": 0,
        "minLinesOfCodeToChange": 0,
        "maxLinesOfCodeToChange": 0
      },
      "ruleInstances": [],
      "features": []
    }
  ],
  "rules": {}
}